eratools/__init__.py
eratools/_version.py
eratools/accessor.py
eratools/geopotential.py
eratools/modeldefs.py
eratools/utils/__init__.py
eratools/utils/fetchERA.py
eratools-0.1.0.dist-info/METADATA
eratools-0.1.0.dist-info/RECORD
eratools-0.1.0.dist-info/WHEEL
eratools-0.1.0.dist-info/top_level.txt
