Metadata-Version: 2.1
Name: eratools
Version: 0.1.0
Summary: A package extending xarray for use with ECMWF ERA model level data.
Home-page: https://arggit.usask.ca/Chris/eratools
Author: Chris Roth
Author-email: chris.roth@usask.ca
License: UNKNOWN
Platform: UNKNOWN
Classifier: Programming Language :: Python :: 3
Classifier: License :: OSI Approved :: MIT License
Classifier: Operating System :: OS Independent
